ome/__init__.py
ome/io/__init__.py
ome/io/reader/__init__.py
ome/io/reader/base.py
ome/io/reader/dsec.py
ome/io/reader/m3ed.py
ome/io/reader/mvsec.py
ome/io/reader/tumvie.py
ome/io/reader/vector.py
ome/io/sample/__init__.py
ome/io/sample/uniform.py
ome/repr/__init__.py
ome/repr/frame.py
ome/repr/voxel.py
ome/scale/common.py
ome/utils/__init__.py
ome/utils/_nvidia_cdll_hook.py
ome/utils/sync.py
ome/utils/timer.py
ome-0.1.1.dist-info/WHEEL
ome-0.1.1.dist-info/METADATA
ome-0.1.1.dist-info/RECORD
