Metadata-Version: 2.3
Name: ome
Version: 0.1.1
Summary: Oh My Event - Just a busybox for Event Camera
Requires-Dist: h5py>=3.14.0
Requires-Dist: hdf5plugin>=5.1.0
Requires-Dist: cupy-cuda12x>=13.6.0
Requires-Dist: numba>=0.62.0
Requires-Dist: nvidia-cuda-nvrtc-cu12==12.8.*
Requires-Dist: nvidia-cuda-runtime-cu12==12.8.*
Requires-Python: >=3.12
